__init__.py
ticket_extractors/__init__.py
ticket_extractors/base_extractor.py
ticket_extractors/config.py
ticket_extractors/confluence_extractor.py
ticket_extractors/jira_extractor.py
ticket_extractors/memory_manager.py
ticket_extractors/person_analyzer.py
ticket_extractors/rate_limiter.py
ticket_extractors/url_analyzer.py
ticket_extractors/webpage_extractor.py
ticket_miner-1.0.0.dist-info/LICENSE
ticket_miner-1.0.0.dist-info/METADATA
ticket_miner-1.0.0.dist-info/WHEEL
ticket_miner-1.0.0.dist-info/top_level.txt
ticket_miner-1.0.0.dist-info/RECORD
