Metadata-Version: 2.2
Name: ticket-miner
Version: 1.0.0
Summary: a python library designed to grab a Jira ticket and scrape ALL of the related and referenced content (and scrape referenced Confluence pages or help center pages for their full content) like a human reviewer would do to try and understand what was going on, and return structured JSON to make it easy to pass to an LLM / ChatGPT / GenAI Etc
Author-email: Your Organization <maintainers@example.com>
License: MIT
Keywords: ticket mining,knowledge base,jira,confluence,documentation
Classifier: Development Status :: 4 - Beta
Classifier: Intended Audience :: Developers
Classifier: License :: OSI Approved :: MIT License
Classifier: Operating System :: OS Independent
Classifier: Programming Language :: Python :: 3
Classifier: Programming Language :: Python :: 3.8
Classifier: Programming Language :: Python :: 3.9
Classifier: Programming Language :: Python :: 3.10
Classifier: Programming Language :: Python :: 3.11
Classifier: Topic :: Software Development :: Libraries :: Python Modules
Requires-Python: >=3.8
License-File: LICENSE
Requires-Dist: atlassian-python-api>=3.41.0
Requires-Dist: python-dotenv>=1.0.0
Requires-Dist: html2text>=2020.1.16
Requires-Dist: urllib3>=2.0.0
Requires-Dist: requests>=2.31.0
Requires-Dist: psutil>=5.9.0
Requires-Dist: aiohttp>=3.9.0
Provides-Extra: dev
Requires-Dist: pytest>=7.0.0; extra == "dev"
Requires-Dist: black>=22.0.0; extra == "dev"
Requires-Dist: isort>=5.0.0; extra == "dev"
Requires-Dist: flake8>=4.0.0; extra == "dev"
